dls_mainiac_lib/__init__.py
dls_mainiac_lib/__main__.py
dls_mainiac_lib/_version.py
dls_mainiac_lib/assert_helpers.py
dls_mainiac_lib/duplicate.py
dls_mainiac_lib/log666.py
dls_mainiac_lib/mainiac.py
dls_mainiac_lib/version.py
dls_mainiac-4.1.0.dist-info/METADATA
dls_mainiac-4.1.0.dist-info/WHEEL
dls_mainiac-4.1.0.dist-info/entry_points.txt
dls_mainiac-4.1.0.dist-info/top_level.txt
dls_mainiac-4.1.0.dist-info/RECORD
